gui/__init__.py
gui/pade_frontend.py
gui/maxent_bosonic_frontend.py
gui/gui_backend.py
gui/maxent_frontend.py
gui/pade_ui.py
gui/maxent_ui.py
gui/maxent_bosonic_ui.py
ana_cont-1.1.2.data/scripts/maxent_bosonic.py
ana_cont-1.1.2.data/scripts/pade.py
ana_cont-1.1.2.data/scripts/maxent.py
ana_cont/continuation.py
ana_cont/__init__.py
ana_cont/pade.pyx
ana_cont/solvers.py
ana_cont/kernels.py
ana_cont/pade.cpython-312-x86_64-linux-gnu.so
ana_cont-1.1.2.dist-info/WHEEL
ana_cont-1.1.2.dist-info/RECORD
ana_cont-1.1.2.dist-info/top_level.txt
ana_cont-1.1.2.dist-info/LICENSE
ana_cont-1.1.2.dist-info/METADATA
